langchain_google_genai/__init__.py
langchain_google_genai/_common.py
langchain_google_genai/_compat.py
langchain_google_genai/_enums.py
langchain_google_genai/_function_utils.py
langchain_google_genai/_image_utils.py
langchain_google_genai/chat_models.py
langchain_google_genai/embeddings.py
langchain_google_genai/llms.py
langchain_google_genai/py.typed
langchain_google_genai/utils.py
langchain_google_genai/data/__init__.py
langchain_google_genai/data/_profiles.py
langchain_google_genai/data/profile_augmentations.toml
langchain_google_genai-4.1.0.dist-info/METADATA
langchain_google_genai-4.1.0.dist-info/WHEEL
langchain_google_genai-4.1.0.dist-info/licenses/LICENSE
langchain_google_genai-4.1.0.dist-info/RECORD
