Metadata-Version: 2.4
Name: langchain-google-genai
Version: 4.1.0
Summary: An integration package connecting Google's genai package and LangChain
Project-URL: Homepage, https://docs.langchain.com/oss/python/integrations/providers/google
Project-URL: Documentation, https://reference.langchain.com/python/integrations/langchain_google_genai/
Project-URL: Source, https://github.com/langchain-ai/langchain-google/tree/master/libs/genai
Project-URL: Changelog, https://github.com/langchain-ai/langchain-google/releases?q=%22genai%22
Project-URL: Twitter, https://x.com/LangChainAI
Project-URL: Slack, https://www.langchain.com/join-community
Project-URL: Reddit, https://www.reddit.com/r/LangChain/
License: MIT
License-File: LICENSE
Requires-Python: <4.0.0,>=3.10.0
Requires-Dist: filetype<2.0.0,>=1.2.0
Requires-Dist: google-genai<2.0.0,>=1.53.0
Requires-Dist: langchain-core<2.0.0,>=1.2.2
Requires-Dist: pydantic<3.0.0,>=2.0.0
